bayesiannet/__init__.py
bayesiannet-0.0.1.dist-info/LICENSE.txt
bayesiannet-0.0.1.dist-info/METADATA
bayesiannet-0.0.1.dist-info/WHEEL
bayesiannet-0.0.1.dist-info/top_level.txt
bayesiannet-0.0.1.dist-info/RECORD
