Metadata-Version: 2.1
Name: bayesiannet
Version: 0.0.1
Summary: Bayesian Network
Home-page: https://github.com/zohimchandani/CQCtest
Author: Zohim Chandani
Author-email: zohim.chandani@hotmail.co.uk
License: UNKNOWN
Project-URL: Bug Tracker, https://github.com/pypa/sampleproject/issues
Platform: UNKNOWN
Classifier: Programming Language :: Python :: 3
Classifier: License :: OSI Approved :: MIT License
Classifier: Operating System :: OS Independent
Requires-Python: >=3.6
